{"data":{"allContentfulMainNav":{"edges":[{"node":{"navItems":[{"navItemText":"Customers","navItemUrl":"#Our Clients"},{"navItemText":"Career","navItemUrl":"#Our Experts"},{"navItemText":"Empowerment and Tech","navItemUrl":"/"},{"navItemText":"Blog","navItemUrl":"/blog/"},{"navItemText":"Contact","navItemUrl":"#Get in touch"}]}}]},"allContentfulLegalNav":{"edges":[{"node":{"navItems":[{"navItemText":"Privacy Policy","navItemUrl":"/privacy/"},{"navItemText":"Imprint","navItemUrl":"/imprint"},{"navItemText":"Modern Slavery Policy","navItemUrl":"/modernSlaveryPolicy"}]}}]}}}